airflow_slurm_executor/__init__.py
airflow_slurm_executor/slurm_control.py
airflow_slurm_executor/slurm_executor.py
airflow_slurm_executor/slurm_executor_plugin.py
airflow_slurm_executor-0.0.2.dist-info/LICENSE
airflow_slurm_executor-0.0.2.dist-info/METADATA
airflow_slurm_executor-0.0.2.dist-info/WHEEL
airflow_slurm_executor-0.0.2.dist-info/top_level.txt
airflow_slurm_executor-0.0.2.dist-info/RECORD
