Metadata-Version: 2.1
Name: airflow_slurm_executor
Version: 0.0.2
Summary: Plugin for Airflow to connect to slurm clusters
Home-page: https://github.com/sunset666/Airflow-Slurm-Executor
Author: Sunset666
Author-email: sunset666@sunset666.net
Classifier: Programming Language :: Python :: 3
Classifier: License :: OSI Approved :: Apache Software License
Classifier: Operating System :: OS Independent
Requires-Python: >=3.6
License-File: LICENSE
Requires-Dist: apache-airflow >=2.5.3
